data_pipeline/setup.py
data_pipeline/common/__init__.py
data_pipeline/common/state_manager.py
data_pipeline/ingestion/__init__.py
data_pipeline/ingestion/base_ingestor.py
data_pipeline/ingestion/mf4_ingestor.py
data_pipeline/ingestion/rosbag_ingestor.py
data_pipeline/ingestion/ros2_msg_parser/__init__.py
data_pipeline/ingestion/ros2_msg_parser/parser.py
data_pipeline/ingestion/ros2_msg_parser/rosbags_image.py
data_pipeline/ingestion/ros2_msg_parser/rosbags_pointcloud.py
data_pipeline/preprocessing/__init__.py
data_pipeline/preprocessing/compute_mf_labels.py
data_pipeline/preprocessing/config.py
data_pipeline/preprocessing/h5_utils.py
data_pipeline/preprocessing/label_extractors.py
data_pipeline/preprocessing/normalizers.py
data_pipeline/preprocessing/preprocess_base.py
data_pipeline/preprocessing/preprocess_labels.py
data_pipeline/preprocessing/preprocess_pointcloud.py
data_pipeline/preprocessing/preprocess_spconv.py
data_pipeline/processing/__init__.py
data_pipeline/processing/h5_merger.py
data_pipeline/processing/metadata_functions.py
data_pipeline/validation/mf4_h5_validator.py
data_pipeline/validation/mf4_validator.py
submodules/dataset-analysis/main.py
submodules/dataset-analysis/src/config.py
submodules/dataset-analysis/src/extend_rfmu_data.py
submodules/dataset-analysis/src/h5_layout.py
submodules/dataset-analysis/src/magic_formula_fitting/__init__.py
submodules/dataset-analysis/src/magic_formula_fitting/fit_parameters.py
submodules/dataset-analysis/src/magic_formula_fitting/fitting_algorithms.py
submodules/dataset-analysis/src/magic_formula_fitting/parameters.py
submodules/dataset-analysis/src/magic_formula_fitting/tire_models.py
submodules/dataset-analysis/src/utils/__init__.py
submodules/dataset-analysis/src/utils/file_utils.py
fast_data_pipeline-0.3.2.dist-info/METADATA
fast_data_pipeline-0.3.2.dist-info/WHEEL
fast_data_pipeline-0.3.2.dist-info/top_level.txt
fast_data_pipeline-0.3.2.dist-info/RECORD
