Metadata-Version: 2.4
Name: fast_data_pipeline
Version: 0.3.2
Summary: A package for processing MF4 and Rosbag data.
Author-email: Bora Pilav <bbpilav@gmail.com>
Classifier: Programming Language :: Python :: 3
Classifier: License :: OSI Approved :: MIT License
Classifier: Operating System :: OS Independent
Requires-Python: >=3.8
Requires-Dist: numpy==2.2.6
Requires-Dist: pandas
Requires-Dist: h5py
Requires-Dist: tables
Requires-Dist: pyyaml
Requires-Dist: opencv-python-headless
Requires-Dist: rosbags==0.11.0
Requires-Dist: asammdf
Requires-Dist: tqdm
Requires-Dist: joblib
Requires-Dist: loguru
Requires-Dist: torch
Requires-Dist: scipy
Requires-Dist: kornia
Requires-Dist: shapely
